risk_assessment_pakage/__init__.py
risk_assessment_pakage/config.yaml
risk_assessment_pakage/example.py
risk_assessment_pakage/main.py
enterprise_risk_assessment-0.1.3.dist-info/METADATA
enterprise_risk_assessment-0.1.3.dist-info/WHEEL
enterprise_risk_assessment-0.1.3.dist-info/entry_points.txt
enterprise_risk_assessment-0.1.3.dist-info/top_level.txt
enterprise_risk_assessment-0.1.3.dist-info/RECORD
